PrettyConsole/PrettyConsole.py
PrettyConsole/__init__.py
PrettyConsole-0.1.0.dist-info/LICENSE
PrettyConsole-0.1.0.dist-info/METADATA
PrettyConsole-0.1.0.dist-info/WHEEL
PrettyConsole-0.1.0.dist-info/top_level.txt
PrettyConsole-0.1.0.dist-info/RECORD
