Metadata-Version: 2.1
Name: PrettyConsole
Version: 0.1.0
Summary: A easy way to use colors in the terminal via ANSI Escape Codes
Author: Erick Fernando Carvalho Sanchez
Author-email: carvalhosanchezerickfernando@gmail.com
License: BSD 3-Clause License
Classifier: Programming Language :: Python :: 3
Classifier: License :: OSI Approved :: BSD License
Classifier: Operating System :: OS Independent
Requires-Python: >=3.6
License-File: LICENSE
